midv500/__init__.py
midv500/convert_dataset.py
midv500/download_dataset.py
midv500/utils.py
tests/__init__.py
tests/test_unit.py
midv500-0.2.1.dist-info/LICENSE
midv500-0.2.1.dist-info/METADATA
midv500-0.2.1.dist-info/WHEEL
midv500-0.2.1.dist-info/top_level.txt
midv500-0.2.1.dist-info/RECORD
