Metadata-Version: 2.1
Name: midv500
Version: 0.2.1
Summary: Download and convert MIDV-500 annotations to COCO instance segmentation format
Home-page: https://github.com/fcakyon/midv500
Author: Fatih Cagatay Akyon
Author-email: 
License: UNKNOWN
Platform: UNKNOWN
Classifier: Programming Language :: Python :: 3
Classifier: License :: OSI Approved :: MIT License
Classifier: Operating System :: OS Independent
Requires-Python: >=3.5
Requires-Dist: opencv-python (>=3.4.8.29)
Requires-Dist: numpy
Requires-Dist: tqdm (>=4.43.0)
